canomaly/__init__.py
canomaly/searchtools.py
canomaly-0.0.5.dist-info/LICENSE
canomaly-0.0.5.dist-info/METADATA
canomaly-0.0.5.dist-info/WHEEL
canomaly-0.0.5.dist-info/top_level.txt
canomaly-0.0.5.dist-info/RECORD
